pack_mm-0.1.11.dist-info/METADATA
pack_mm-0.1.11.dist-info/WHEEL
pack_mm-0.1.11.dist-info/entry_points.txt
pack_mm-0.1.11.dist-info/licenses/LICENSE
pack_mm/__init__.py
pack_mm/cli/packmm.py
pack_mm/core/core.py
pack_mm-0.1.11.dist-info/RECORD
