Metadata-Version: 2.1
Name: pack-mm
Version: 0.1.11
Summary: packing materials and molecules in boxes using for machine learnt interatomic potentials
Author: Alin M. Elena
Classifier: Programming Language :: Python
Classifier: Programming Language :: Python :: 3.10
Classifier: Programming Language :: Python :: 3.11
Classifier: Programming Language :: Python :: 3.12
Classifier: Intended Audience :: Science/Research
Classifier: License :: OSI Approved :: MIT License
Classifier: Natural Language :: English
Classifier: Development Status :: 4 - Beta
Project-URL: Repository, https://github.com/ddmms/pack-mm/
Project-URL: Documentation, https://ddmms.github.io/pack-mm/
Requires-Python: >=3.10
Requires-Dist: janus-core[mace]>=0.7.2
Requires-Dist: typer<1.0.0,>=0.12.5
Requires-Dist: typer-config<2.0.0,>=1.4.2
